bear_installation_tool/__init__.py
bear_installation_tool/installation_tool.py
ear_installation_tool-0.0.5.dist-info/LICENSE
ear_installation_tool-0.0.5.dist-info/METADATA
ear_installation_tool-0.0.5.dist-info/WHEEL
ear_installation_tool-0.0.5.dist-info/entry_points.txt
ear_installation_tool-0.0.5.dist-info/top_level.txt
ear_installation_tool-0.0.5.dist-info/RECORD
